verumverify/__init__.py
verumverify/crypto_svc.py
verumverify/main.py
verumverify/retrieval_svc.py
verumverify/status_svc.py
verumverify/video_svc.py
verumverify-0.0.3.dist-info/AUTHORS.rst
verumverify-0.0.3.dist-info/LICENSE
verumverify-0.0.3.dist-info/METADATA
verumverify-0.0.3.dist-info/WHEEL
verumverify-0.0.3.dist-info/entry_points.txt
verumverify-0.0.3.dist-info/top_level.txt
verumverify-0.0.3.dist-info/RECORD
