Metadata-Version: 2.1
Name: verumverify
Version: 0.0.3
Summary: Verifies the authenticity of content published on the Verum Journo portal.
Home-page: https://github.com/Ethosym/verumverify
Author: Ethosymn
Author-email: ethosymn.verum.service@gmail.com
Classifier: Programming Language :: Python :: 3
Classifier: Programming Language :: Python :: 2
Classifier: License :: OSI Approved :: MIT License
Classifier: Operating System :: OS Independent
License-File: LICENSE
License-File: AUTHORS.rst
Requires-Dist: cryptography
Requires-Dist: rfc3161ng
Requires-Dist: click
Requires-Dist: requests
Requires-Dist: pymaybe
